aicodebot/__init__.py
aicodebot/cli.py
aicodebot/coder.py
aicodebot/config.py
aicodebot/helpers.py
aicodebot/input.py
aicodebot/lm.py
aicodebot/output.py
aicodebot/patch.py
aicodebot/prompts.py
aicodebot/commands/__init__.py
aicodebot/commands/alignment.py
aicodebot/commands/commit.py
aicodebot/commands/configure.py
aicodebot/commands/debug.py
aicodebot/commands/review.py
aicodebot/commands/sidekick.py
aicodebot-0.30.0.dist-info/licenses/LICENSE
aicodebot-0.30.0.dist-info/METADATA
aicodebot-0.30.0.dist-info/WHEEL
aicodebot-0.30.0.dist-info/entry_points.txt
aicodebot-0.30.0.dist-info/top_level.txt
aicodebot-0.30.0.dist-info/RECORD
