Metadata-Version: 2.4
Name: aicodebot
Version: 0.30.0
Summary: AI-powered tool for developers, simplifying coding tasks and improving workflow efficiency.
Home-page: https://github.com/TechNickAI/AICodeBot
Author: Nick Sullivan
Keywords: AI,coding,assistant,pair-programming,automation,productivity,workflow,artificial intelligence
Classifier: Development Status :: 4 - Beta
Classifier: Intended Audience :: Developers
Classifier: License :: OSI Approved :: GNU Affero General Public License v3
Classifier: Programming Language :: Python :: 3
Classifier: Programming Language :: Python :: 3.10
Classifier: Programming Language :: Python :: 3.11
Classifier: Programming Language :: Python :: 3.12
Classifier: Programming Language :: Python :: 3.13
Requires-Python: >=3.10
License-File: LICENSE
Requires-Dist: arrow
Requires-Dist: click
Requires-Dist: GitPython
Requires-Dist: humanize
Requires-Dist: langchain_core
Requires-Dist: langchain_anthropic
Requires-Dist: langchain_openai
Requires-Dist: loguru
Requires-Dist: prompt-toolkit
Requires-Dist: pyperclip
Requires-Dist: pyyaml
Requires-Dist: rich
Requires-Dist: tiktoken
Dynamic: author
Dynamic: classifier
Dynamic: description
Dynamic: description-content-type
Dynamic: home-page
Dynamic: keywords
Dynamic: license-file
Dynamic: requires-dist
Dynamic: requires-python
Dynamic: summary
